hifi_solves_run_humanwgs/__init__.py
hifi_solves_run_humanwgs/constants.py
hifi_solves_run_humanwgs/logger.py
hifi_solves_run_humanwgs/upload_and_run.py
hifi_solves_run_humanwgs/workbench.py
hifi_solves_run_humanwgs/__pycache__/__init__.cpython-313.pyc
hifi_solves_run_humanwgs/__pycache__/constants.cpython-313.pyc
hifi_solves_run_humanwgs/__pycache__/logger.cpython-313.pyc
hifi_solves_run_humanwgs/__pycache__/upload_and_run.cpython-313.pyc
hifi_solves_run_humanwgs/__pycache__/workbench.cpython-313.pyc
hifi_solves_run_humanwgs/backends/__init__.py
hifi_solves_run_humanwgs/backends/aws.py
hifi_solves_run_humanwgs/backends/azure.py
hifi_solves_run_humanwgs/backends/gcp.py
hifi_solves_run_humanwgs/backends/parameter_override.py
hifi_solves_run_humanwgs/backends/__pycache__/__init__.cpython-313.pyc
hifi_solves_run_humanwgs/backends/__pycache__/aws.cpython-313.pyc
hifi_solves_run_humanwgs/backends/__pycache__/azure.cpython-313.pyc
hifi_solves_run_humanwgs/backends/__pycache__/gcp.cpython-313.pyc
hifi_solves_run_humanwgs/backends/__pycache__/parameter_override.cpython-313.pyc
hifi_solves_run_humanwgs/instruments/dnastack.sample-sync.json
hifi_solves_run_humanwgs/instruments/transformation.js
hifi_solves_run_humanwgs/workflows/__init__.py
hifi_solves_run_humanwgs/workflows/hifisolves_wrapper.wdl
hifi_solves_run_humanwgs/workflows/input_template.aws-healthomics.json
hifi_solves_run_humanwgs/workflows/input_template.azure.json
hifi_solves_run_humanwgs/workflows/input_template.gcp.json
hifi_solves_run_humanwgs/workflows/HiFi-human-WGS-WDL/.dockstore.yml
hifi_solves_run_humanwgs/workflows/HiFi-human-WGS-WDL/.git
hifi_solves_run_humanwgs/workflows/HiFi-human-WGS-WDL/.gitignore
hifi_solves_run_humanwgs/workflows/HiFi-human-WGS-WDL/.gitmodules
hifi_solves_run_humanwgs/workflows/HiFi-human-WGS-WDL/GRCh38.ref_map.v2p0p0.template.tsv
hifi_solves_run_humanwgs/workflows/HiFi-human-WGS-WDL/GRCh38.tertiary_map.v2p0p0.template.tsv
hifi_solves_run_humanwgs-2.8.3.dist-info/METADATA
hifi_solves_run_humanwgs-2.8.3.dist-info/WHEEL
hifi_solves_run_humanwgs-2.8.3.dist-info/entry_points.txt
hifi_solves_run_humanwgs-2.8.3.dist-info/top_level.txt
hifi_solves_run_humanwgs-2.8.3.dist-info/RECORD
