Metadata-Version: 2.4
Name: hifi_solves_run_humanwgs
Version: 2.8.3
Summary: Upload required files and run [PacBio's Human WGS workflow](https://github.com/PacificBiosciences/HiFi-human-WGS-WDL) via [DNAstack's Workbench](https://omics.ai/workbench/)
Author: DNAstack
Author-email: bioinformatics@dnastack.com
Maintainer: Heather Ward
Maintainer-email: heather@dnastack.com
License: GPLv2
Requires-Python: >=3.13
Requires-Dist: pandas>=2.2.2
Requires-Dist: boto3>=1.34.0
Requires-Dist: dnastack-client-library==v3.1.207
Requires-Dist: azure-storage-blob==12.20.0
Requires-Dist: azure-core==1.30.2
Requires-Dist: google-cloud-storage==2.17.0
Requires-Dist: regex==2024.11.6
Dynamic: author
Dynamic: author-email
Dynamic: description
Dynamic: description-content-type
Dynamic: license
Dynamic: maintainer
Dynamic: maintainer-email
Dynamic: requires-dist
Dynamic: requires-python
Dynamic: summary
